Metadata-Version: 1.1
Name: poeditor-api-wrapper
Version: 0.1
Summary: Python Wrapper for POEditor V2 API
Home-page: http://bitbucket.org/asmuth444/poeditor_api_wrapper
Author: Abhishek Roul
Author-email: asmuth444@gmail.com
License: MIT
Keywords: poeditor api v2
Platform: UNKNOWN
Classifier: Development Status :: 3 - Alpha
Classifier: Topic :: Software Development :: Libraries :: Python Modules
